heteroscedasticity_tests/Glejser_test.py
heteroscedasticity_tests/Heteroscedasticity_test_general.py
heteroscedasticity_tests/Park_test.py
heteroscedasticity_tests/__init__.py
heteroscedasticity_tests-1.4.dist-info/DESCRIPTION.rst
heteroscedasticity_tests-1.4.dist-info/METADATA
heteroscedasticity_tests-1.4.dist-info/RECORD
heteroscedasticity_tests-1.4.dist-info/WHEEL
heteroscedasticity_tests-1.4.dist-info/metadata.json
heteroscedasticity_tests-1.4.dist-info/top_level.txt
