Metadata-Version: 2.0
Name: heteroscedasticity-tests
Version: 1.4
Summary: Tests for heteroscedasticity, Park and Glejser
Home-page: UNKNOWN
Author: Inga Kuznetsova
Author-email: kuzn137@gmail.com
License: UNKNOWN
Platform: UNKNOWN
